wing.py
wingsdk-0.0.6.dist-info/METADATA
wingsdk-0.0.6.dist-info/WHEEL
wingsdk-0.0.6.dist-info/top_level.txt
wingsdk-0.0.6.dist-info/RECORD
